{
  "$schema": "https://developer.microsoft.com/json-schemas/fabric/item/report/definition/visualContainer/2.6.0/schema.json",
  "name": "2ee30604486d94048619",
  "position": {
    "x": 7.3616103522645577,
    "y": 98.461538461538467,
    "z": 0,
    "height": 302.74622573688,
    "width": 624.8166786484544,
    "tabOrder": 0
  },
  "visual": {
    "visualType": "scatterChart",
    "query": {
      "queryState": {
        "X": {
          "projections": [
            {
              "field": {
                "Column": {
                  "Expression": {
                    "SourceRef": {
                      "Entity": "DadosMarketing"
                    }
                  },
                  "Property": "Salario Anual"
                }
              },
              "queryRef": "Sum(DadosMarketing.Salario Anual)",
              "nativeQueryRef": "Salario Anual",
              "active": true
            }
          ]
        },
        "Y": {
          "projections": [
            {
              "field": {
                "Measure": {
                  "Expression": {
                    "SourceRef": {
                      "Entity": "DadosMarketing"
                    }
                  },
                  "Property": "TotalGasto"
                }
              },
              "queryRef": "DadosMarketing.TotalGasto",
              "nativeQueryRef": "TotalGasto"
            }
          ]
        }
      }
    },
    "objects": {
      "categoryAxis": [
        {
          "properties": {
            "logAxisScale": {
              "expr": {
                "Literal": {
                  "Value": "false"
                }
              }
            },
            "show": {
              "expr": {
                "Literal": {
                  "Value": "false"
                }
              }
            }
          }
        }
      ],
      "valueAxis": [
        {
          "properties": {
            "show": {
              "expr": {
                "Literal": {
                  "Value": "false"
                }
              }
            }
          }
        }
      ]
    },
    "visualContainerObjects": {
      "title": [
        {
          "properties": {
            "text": {
              "expr": {
                "Literal": {
                  "Value": "'Total de gastos X Salário anual'"
                }
              }
            },
            "alignment": {
              "expr": {
                "Literal": {
                  "Value": "'center'"
                }
              }
            }
          }
        }
      ],
      "dropShadow": [
        {
          "properties": {
            "show": {
              "expr": {
                "Literal": {
                  "Value": "true"
                }
              }
            }
          }
        }
      ]
    },
    "drillFilterOtherVisuals": true
  }
}